.project-version
LICENSE
MANIFEST.in
README.md
pyproject.toml
setup.cfg
setup.py
diagrams_yaml/__init__.py
diagrams_yaml/entrypoint.py
diagrams_yaml/enums.py
diagrams_yaml/resources.py
diagrams_yaml/schema.py
diagrams_yaml.egg-info/PKG-INFO
diagrams_yaml.egg-info/SOURCES.txt
diagrams_yaml.egg-info/dependency_links.txt
diagrams_yaml.egg-info/entry_points.txt
diagrams_yaml.egg-info/requires.txt
diagrams_yaml.egg-info/top_level.txt
requirements/project.txt