Metadata-Version: 2.1
Name: diagrams-yaml
Version: 0.0.8
Summary: Diagram as Code in a declarative way using YAML for drawing cloud system architectures.
Home-page: https://github.com/dmytrostriletskyi/diagrams-yaml
Author: Dmytro Striletskyi
Author-email: dmytro.striletskyi@gmail.com
License: MIT
Project-URL: Issue Tracker, https://github.com/dmytrostriletskyi/diagrams-yaml/issues
Project-URL: Source Code, https://github.com/dmytrostriletskyi/diagrams-yaml
Project-URL: Download, https://github.com/dmytrostriletskyi/diagrams-yaml/tags
Platform: UNKNOWN
Classifier: Operating System :: OS Independent
Classifier: Intended Audience :: Developers
Classifier: License :: OSI Approved :: MIT License
Classifier: Programming Language :: Python :: 3.11
License-File: LICENSE
